state2inventory/__init__.py
state2inventory/output/__init__.py
state2inventory/output/inventory.py
state2inventory/provider/__init__.py
state2inventory/provider/terraform.py
state2inventory/state2inventory.py
state2inventory-1.1.1.dist-info/LICENSE
state2inventory-1.1.1.dist-info/METADATA
state2inventory-1.1.1.dist-info/WHEEL
state2inventory-1.1.1.dist-info/entry_points.txt
state2inventory-1.1.1.dist-info/RECORD
