Metadata-Version: 2.1
Name: state2inventory
Version: 1.1.1
Summary: Generate an Ansible inventory file from an infrastructure state
Home-page: https://gitlab.com/op_so/ansible/state2inventory/
License: MIT
Author: FX Soubirou
Author-email: soubirou@yahoo.fr
Requires-Python: >=3.10,<4.0
Classifier: License :: OSI Approved :: MIT License
Classifier: Operating System :: OS Independent
Classifier: Programming Language :: Python :: 3
Classifier: Programming Language :: Python :: 3.10
Classifier: Programming Language :: Python :: 3.11
Classifier: Programming Language :: Python :: 3.12
Requires-Dist: click (>=8.1.7,<9.0.0)
Project-URL: Documentation, https://op_so.gitlab.io/ansible/state2inventory/
